datastream/__init__.py
datastream/data_input_stream.py
datastream/data_output_stream.py
datastream/stream_wrapper.py
datastream/utils.py
python_datastream-0.1.0.dist-info/LICENSE
python_datastream-0.1.0.dist-info/WHEEL
python_datastream-0.1.0.dist-info/METADATA
python_datastream-0.1.0.dist-info/RECORD
