Metadata-Version: 2.1
Name: python-datastream
Version: 0.1.0
Summary: Read and write not only bytes in python (like DataStream in java)
Author-email: NekoNekoNyan <pasha2001dpa@ya.ru>
Requires-Python: >=3.6
Classifier: License :: OSI Approved :: MIT License
Classifier: Programming Language :: Python :: 3
Project-URL: Home, https://github.com/neko-neko-nyan/datastream
